{
    "format_version": "1.10.0",
    "minecraft:client_entity": {
        "description": {
            "identifier": "camel:cutout_blossom",
            "materials": {
                "default": "entity_alphatest"
            },
            "textures": {
                "default": "textures/entity/projectcamel/cutout_blossom"
            },
            "geometry": {
                "default": "geometry.projectcamel.cutout.blossom"
            },
            "render_controllers": ["controller.render.default"]
        }
    }
}
